wxautoz/__init__.py
wxautoz/exceptions.py
wxautoz/languages.py
wxautoz/logger.py
wxautoz/param.py
wxautoz/test_get_messages.py
wxautoz/test_get_messages_brief.py
wxautoz/uiautomation.py
wxautoz/win32_background_click.py
wxautoz/wx.py
wxautoz/msgs/__init__.py
wxautoz/msgs/attr.py
wxautoz/msgs/base.py
wxautoz/msgs/friend.py
wxautoz/msgs/msg.py
wxautoz/msgs/self.py
wxautoz/msgs/type.py
wxautoz/ui/__init__.py
wxautoz/ui/base.py
wxautoz/ui/chatbox.py
wxautoz/ui/component.py
wxautoz/ui/main.py
wxautoz/ui/navigationbox.py
wxautoz/ui/sessionbox.py
wxautoz/utils/__init__.py
wxautoz/utils/tools.py
wxautoz/utils/win32.py
wxautoz-0.1.2.dist-info/licenses/LICENSE
wxautoz-0.1.2.dist-info/METADATA
wxautoz-0.1.2.dist-info/WHEEL
wxautoz-0.1.2.dist-info/top_level.txt
wxautoz-0.1.2.dist-info/RECORD
