Metadata-Version: 2.4
Name: wxautoz
Version: 0.1.2
Summary: A Python toolkit for automating WeChat tasks on Windows
Author-email: "laychou666, SHLAMING" <2523385776@qq.com>
License: MIT
Project-URL: Homepage, https://https://github.com/laychou666/wxautoz
Requires-Python: >=3.8
License-File: LICENSE
Requires-Dist: pywin32
Requires-Dist: uiautomation
Requires-Dist: colorama
Requires-Dist: pyperclip
Requires-Dist: psutil
Requires-Dist: pillow
Dynamic: license-file
